nexent/__init__.py
nexent/container/__init__.py
nexent/container/container_client_base.py
nexent/container/container_client_factory.py
nexent/container/docker_client.py
nexent/container/docker_config.py
nexent/core/__init__.py
nexent/core/agents/__init__.py
nexent/core/agents/agent_model.py
nexent/core/agents/core_agent.py
nexent/core/agents/nexent_agent.py
nexent/core/agents/run_agent.py
nexent/core/models/__init__.py
nexent/core/models/embedding_model.py
nexent/core/models/message_utils.py
nexent/core/models/openai_llm.py
nexent/core/models/openai_long_context_model.py
nexent/core/models/openai_vlm.py
nexent/core/models/stt_model.py
nexent/core/models/tts_model.py
nexent/core/nlp/__init__.py
nexent/core/nlp/stopwords.py
nexent/core/nlp/tokenizer.py
nexent/core/prompts/analyze_file.yaml
nexent/core/prompts/analyze_file_en.yaml
nexent/core/prompts/analyze_image.yaml
nexent/core/prompts/analyze_image_en.yaml
nexent/core/tools/__init__.py
nexent/core/tools/analyze_image_tool.py
nexent/core/tools/analyze_text_file_tool.py
nexent/core/tools/create_directory_tool.py
nexent/core/tools/create_file_tool.py
nexent/core/tools/datamate_search_tool.py
nexent/core/tools/delete_directory_tool.py
nexent/core/tools/delete_file_tool.py
nexent/core/tools/dify_search_tool.py
nexent/core/tools/exa_search_tool.py
nexent/core/tools/get_email_tool.py
nexent/core/tools/knowledge_base_search_tool.py
nexent/core/tools/linkup_search_tool.py
nexent/core/tools/list_directory_tool.py
nexent/core/tools/move_item_tool.py
nexent/core/tools/read_file_tool.py
nexent/core/tools/send_email_tool.py
nexent/core/tools/tavily_search_tool.py
nexent/core/tools/terminal_tool.py
nexent/core/utils/__init__.py
nexent/core/utils/constants.py
nexent/core/utils/favicon_extractor.py
nexent/core/utils/observer.py
nexent/core/utils/prompt_template_utils.py
nexent/core/utils/tools_common_message.py
nexent/data_process/__init__.py
nexent/data_process/base.py
nexent/data_process/core.py
nexent-1.7.10.dist-info/METADATA
nexent-1.7.10.dist-info/WHEEL
nexent-1.7.10.dist-info/top_level.txt
nexent-1.7.10.dist-info/RECORD
