Metadata-Version: 2.4
Name: nexent
Version: 1.7.10
Summary: Nexent Agent Framework
Author: Nexent Dev Team
Keywords: agent,ai,framework
Classifier: Intended Audience :: Developers
Classifier: Programming Language :: Python :: 3
Classifier: Programming Language :: Python :: 3.10
Requires-Python: >=3.10
Requires-Dist: aiofiles>=24.1.0
Requires-Dist: elasticsearch==8.17.2
Requires-Dist: exa_py==1.14.0
Requires-Dist: httpx[socks]>=0.28.1
Requires-Dist: numpy>=1.26.4
Requires-Dist: openai>=1.69.0
Requires-Dist: openpyxl>=3.1.5
Requires-Dist: pydantic[email]>=2.11.1
Requires-Dist: python-dotenv>=1.1.0
Requires-Dist: PyYAML>=6.0.1
Requires-Dist: Requests>=2.32.3
Requires-Dist: rich>=13.9.4
Requires-Dist: setuptools>=75.1.0
Requires-Dist: websockets>=14.2
Requires-Dist: smolagents[mcp]==1.23.0
Requires-Dist: Pillow>=10.0.0
Requires-Dist: aiohttp>=3.1.13
Requires-Dist: jieba>=0.42.1
Requires-Dist: boto3>=1.37.34
Requires-Dist: botocore>=1.37.34
Requires-Dist: python-multipart>=0.0.20
Requires-Dist: mcpadapt>=0.1.13
Requires-Dist: mcp<1.23,>=1.19.0
Requires-Dist: fastmcp==2.12.0
Requires-Dist: docker>=7.0.0
Requires-Dist: tiktoken>=0.5.0
Requires-Dist: tavily-python
Requires-Dist: linkup-sdk
Requires-Dist: paramiko>=3.4.0
Requires-Dist: linkup-sdk
Requires-Dist: mem0ai>=0.1.117
Provides-Extra: quality
Requires-Dist: ruff>=0.9.0; extra == "quality"
Requires-Dist: pytest>=8.1.0; extra == "quality"
Provides-Extra: data-process
Requires-Dist: unstructured[all-docs]; extra == "data-process"
Provides-Extra: performance
Requires-Dist: opentelemetry-api==1.20.0; extra == "performance"
Requires-Dist: opentelemetry-sdk==1.20.0; extra == "performance"
Requires-Dist: opentelemetry-semantic-conventions==0.41b0; extra == "performance"
Requires-Dist: opentelemetry-instrumentation==0.41b0; extra == "performance"
Requires-Dist: opentelemetry-instrumentation-fastapi==0.41b0; extra == "performance"
Requires-Dist: opentelemetry-instrumentation-requests==0.41b0; extra == "performance"
Requires-Dist: opentelemetry-exporter-jaeger; extra == "performance"
Requires-Dist: opentelemetry-exporter-prometheus; extra == "performance"
Requires-Dist: prometheus-client; extra == "performance"
Provides-Extra: dev
Requires-Dist: nexent[data_process,performance,quality]; extra == "dev"
